athena_type_converter/__init__.py
athena_type_converter/_meta_data.py
athena_type_converter/_results_convertors.py
athena_type_converter/_type_converters.py
athena_type_converter-0.0.3.dist-info/LICENSE
athena_type_converter-0.0.3.dist-info/METADATA
athena_type_converter-0.0.3.dist-info/WHEEL
athena_type_converter-0.0.3.dist-info/top_level.txt
athena_type_converter-0.0.3.dist-info/RECORD
