Metadata-Version: 2.1
Name: athena-type-converter
Version: 0.0.3
Summary: Helper functions to convert types returned from Athena into Python types
Home-page: https://github.com/QuiNovas/athena-type-converter
Author: Joseph Wortmann
Author-email: joseph.wortmann@gmail.com
License: APL 2.0
Keywords: quinovas
Platform: UNKNOWN
Classifier: Development Status :: 3 - Alpha
Classifier: Topic :: System :: Software Distribution
Classifier: Intended Audience :: Developers
Classifier: License :: OSI Approved :: Apache Software License
Classifier: Programming Language :: Python :: 3.7
